{
  "Version": "2012-10-17",
  "Statement": [
    {
      "Sid": "ECRPull",
      "Effect": "Allow",
      "Action": [
        "ecr:GetAuthorizationToken",
        "ecr:BatchCheckLayerAvailability",
        "ecr:GetDownloadUrlForLayer",
        "ecr:BatchGetImage"
      ],
      "Resource": "*"
    },
    {
      "Sid": "CloudWatchLogs",
      "Effect": "Allow",
      "Action": [
        "logs:CreateLogStream",
        "logs:PutLogEvents"
      ],
      "Resource": "arn:aws:logs:AWS_REGION:ACCOUNT_ID:log-group:/medipulse/*"
    },
    {
      "Sid": "SecretsManagerRead",
      "Effect": "Allow",
      "Action": [
        "secretsmanager:GetSecretValue"
      ],
      "Resource": "arn:aws:secretsmanager:AWS_REGION:ACCOUNT_ID:secret:medipulse/*"
    }
  ]
}
